_yaml/__init__.py
yaml/__init__.py
yaml/_yaml.cpython-313-aarch64-linux-gnu.so
yaml/composer.py
yaml/constructor.py
yaml/cyaml.py
yaml/dumper.py
yaml/emitter.py
yaml/error.py
yaml/events.py
yaml/loader.py
yaml/nodes.py
yaml/parser.py
yaml/reader.py
yaml/registry.py
yaml/representer.py
yaml/resolver.py
yaml/scanner.py
yaml/serializer.py
yaml/tokens.py
pyyaml_ft-7.0.1.dist-info/METADATA
pyyaml_ft-7.0.1.dist-info/WHEEL
pyyaml_ft-7.0.1.dist-info/top_level.txt
pyyaml_ft-7.0.1.dist-info/RECORD
pyyaml_ft-7.0.1.dist-info/licenses/LICENSE
