Metadata-Version: 2.4
Name: PyYAML-ft
Version: 7.0.1
Summary: YAML parser and emitter for Python with support for free-threading
Home-page: https://github.com/Quansight-Labs/pyyaml/
Download-URL: https://pypi.org/project/PyYAML-ft/
Author: Lysandros Nikolaou
Author-email: lisandrosnik@gmail.com
License: MIT
Project-URL: Bug Tracker, https://github.com/Quansight-Labs/pyyaml/issues
Project-URL: CI, https://github.com/Quansight-Labs/pyyaml/actions
Project-URL: Documentation, https://pyyaml.org/wiki/PyYAMLDocumentation
Project-URL: Mailing lists, http://lists.sourceforge.net/lists/listinfo/yaml-core
Project-URL: Source Code, https://github.com/Quansight-Labs/pyyaml
Platform: Any
Classifier: Development Status :: 5 - Production/Stable
Classifier: Intended Audience :: Developers
Classifier: License :: OSI Approved :: MIT License
Classifier: Operating System :: OS Independent
Classifier: Programming Language :: Cython
Classifier: Programming Language :: Python
Classifier: Programming Language :: Python :: 3.13
Classifier: Programming Language :: Python :: Implementation :: CPython
Classifier: Programming Language :: Python :: Implementation :: PyPy
Classifier: Topic :: Software Development :: Libraries :: Python Modules
Classifier: Topic :: Text Processing :: Markup
Requires-Python: >=3.13
License-File: LICENSE
Dynamic: author
Dynamic: author-email
Dynamic: classifier
Dynamic: description
Dynamic: description-content-type
Dynamic: download-url
Dynamic: home-page
Dynamic: license
Dynamic: license-file
Dynamic: platform
Dynamic: project-url
Dynamic: requires-python
Dynamic: summary
